[
    {
        "merchantName": "MaXpeedingrods",
        "endDate": "11/08/2024",
        "title": "Summer Sale",
        "trackingURL": "https://www.shareasale.com/u.cfm?d=1123724&m=83538&u=233101",
        "category": "Automotive",
        "description": "use code &quot;SU08&quot; enjoy 8% off at maxpeedingrods.com",
        "couponCode": "SU08"
    },
    {
        "merchantName": "MaXpeedingrods",
        "endDate": "06/08/2024",
        "title": "Independence Day",
        "trackingURL": "https://www.shareasale.com/u.cfm?d=1121422&m=83538&u=233101",
        "category": "Automotive",
        "description": "",
        "couponCode": "4JUL"
    }
]